setup.py
sunnyday/__init__.py
sunnyday/sunnyday.py
sunnyday_openweather.egg-info/PKG-INFO
sunnyday_openweather.egg-info/SOURCES.txt
sunnyday_openweather.egg-info/dependency_links.txt
sunnyday_openweather.egg-info/top_level.txt