Metadata-Version: 2.1
Name: sunnyday-openweather
Version: 2.0.0
Summary: Weather forecast data
Home-page: UNKNOWN
Author: Kasia Zysko
License: MIT
Keywords: weather,forecast,openweather
Platform: UNKNOWN
Classifier: Development Status :: 3 - Alpha
Classifier: Topic :: Software Development :: Build Tools
